feagen/__init__.py
feagen/concat_features.py
feagen/feature_generator.py
feagen/decorators/__init__.py
feagen/decorators/data_generation.py
feagen/decorators/data_type.py
feagen/decorators/decorators.py
feagen-0.3.2.dist-info/DESCRIPTION.rst
feagen-0.3.2.dist-info/METADATA
feagen-0.3.2.dist-info/RECORD
feagen-0.3.2.dist-info/WHEEL
feagen-0.3.2.dist-info/metadata.json
feagen-0.3.2.dist-info/top_level.txt
