Metadata-Version: 2.0
Name: feagen
Version: 0.3.2
Summary: A fast and memory-efficient Python feature generating framework for machine learning.
Home-page: https://github.com/ianlini/feagen
Author: ianlini
Author-email: UNKNOWN
License: UNKNOWN
Platform: UNKNOWN
Classifier: Topic :: Utilities
Classifier: Programming Language :: Python :: 2.7
Classifier: Programming Language :: Python :: 3
Requires-Dist: bistiming
Requires-Dist: h5py
Requires-Dist: mkdir-p
Requires-Dist: numpy
Requires-Dist: six
